{
  "workTasks": [
    {
      "id": "w_1784386196469",
      "t": "횄짜횂짯횂짝횄짚횂쨔횂혻ai 횄짜횂혞횂쨋횄짚횂쩍횂혵횄짠횂쩍횂혩횄짠횂짬횂혲",
      "bonus": 30,
      "done": false
    },
    {
      "id": "w_1784386205910",
      "t": "횄짜횂혞횂쨋횄짚횂쩍횂혵횄짤횂혶횂짖횄짢횂짱횂혮ppt",
      "bonus": 20,
      "done": false
    },
    {
      "id": "w_1784386216613",
      "t": "횄짜횂쩍횂혮횄짢횂짱횂쩐횄짤횂혶횂짖횄짢횂짱횂혮",
      "bonus": 20,
      "done": false
    }
  ],
  "hobbyTasks": [],
  "workToday": {
    "w_1784386196469": {
      "hours": 0,
      "done": false
    },
    "w_1784386205910": {
      "hours": 0,
      "done": false
    },
    "w_1784386216613": {
      "hours": 0,
      "done": false
    }
  },
  "hobbyToday": {},
  "records": {},
  "settings": {
    "workPtsPerHr": 10,
    "hobbyPtsPerCheck": 5,
    "hobbyMaxPerDay": 20
  },
  "2026-07-18": {
    "sleep": true,
    "diet": false,
    "workout": false,
    "ent": false,
    "jyh": false,
    "hyg": false,
    "fam": false,
    "world": false
  }
}